pybasicdtw/__init__.py
pybasicdtw/dtw.py
pybasicdtw/helper.py
pybasicdtw/sdtw.py
pybasicdtw-0.1.0.dist-info/LICENSE
pybasicdtw-0.1.0.dist-info/METADATA
pybasicdtw-0.1.0.dist-info/WHEEL
pybasicdtw-0.1.0.dist-info/top_level.txt
pybasicdtw-0.1.0.dist-info/RECORD
