Metadata-Version: 2.1
Name: pybasicdtw
Version: 0.1.0
Summary: A readable dynamic time warping library.
Author-email: Nikhil Reji <nikhil.reji@live.co.uk>
License: MIT License
Project-URL: Homepage, https://github.com/UomoCaffeLatte/PyBasicDTW
Classifier: Programming Language :: Python :: 3
Classifier: License :: OSI Approved :: MIT License
Classifier: Operating System :: OS Independent
Requires-Python: >=3.7
License-File: LICENSE
Requires-Dist: numpy (>=1.22.3)
Requires-Dist: matplotlib
